VirKraken-0.0.5.data/scripts/spades_virkraken
VirKraken-0.0.5.data/scripts/virkraken
VirKraken-0.0.5.dist-info/DESCRIPTION.rst
VirKraken-0.0.5.dist-info/METADATA
VirKraken-0.0.5.dist-info/RECORD
VirKraken-0.0.5.dist-info/WHEEL
VirKraken-0.0.5.dist-info/metadata.json
VirKraken-0.0.5.dist-info/top_level.txt
virkraken/__init__.py
virkraken/data/TaxID.csv
